{
    "congressNumber": "17th Congress",
    "billNumber": "Senate Bill No. 1396",
    "billTitle": "UNLAWFUL MEMBERSHIP IN TERRORIST ORGANIZATION ACT",
    "dateFiled": "2017-03-15",
    "senatorProposed": [
        "Gregorio B. Honasan II"
    ],
    "scope": "National",
    "status": "Pending in the Committee (3/15/2017)",
    "subjects": [
        "Terrorism"
    ],
    "primaryCommittee": [
        "Public Order and Dangerous Drugs"
    ],
    "secondaryCommittee": [
        "National Defense and Security"
    ]
}