{
    "congressNumber": "17th Congress",
    "billNumber": "Senate Bill No. 1452",
    "billTitle": "COMMUNITY SERVICE ACT OF 2017",
    "dateFiled": "2017-05-15",
    "senatorProposed": [
        "Richard J. Gordon"
    ],
    "scope": "National",
    "status": "Pending in the Committee (5/15/2017)",
    "subjects": [
        "Community Work/Community Service",
        "Revised Penal Code (R.A.No. 3815)"
    ],
    "primaryCommittee": [
        "Justice and Human Rights"
    ],
    "secondaryCommittee": []
}