{
    "congressNumber": "17th Congress",
    "billNumber": "Senate Bill No. 1412",
    "billTitle": "FREE IRRIGATION SERVICES ACT",
    "dateFiled": "2017-03-27",
    "senatorProposed": [
        "Sherwin T. Gatchalian"
    ],
    "scope": "National",
    "status": "Consolidated/Substituted in the Committee Report (5/22/2017)",
    "subjects": [
        "Irrigation",
        "National Irrigation Administration"
    ],
    "primaryCommittee": [
        "Agriculture and Food"
    ],
    "secondaryCommittee": [
        "Finance"
    ]
}