{
    "congressNumber": "17th Congress",
    "billNumber": "Senate Bill No. 1515",
    "billTitle": "THE EXPANDED PHILIPPINE SPORTS COMMISSION ACT OF 2017",
    "dateFiled": "2017-07-26",
    "senatorProposed": [
        "Emmanuel \"Manny\" D. Pacquiao"
    ],
    "scope": "National",
    "status": "Pending in the Committee (7/31/2017)",
    "subjects": [
        "Philippine Sports Commission (PSC)"
    ],
    "primaryCommittee": [
        "Sports"
    ],
    "secondaryCommittee": [
        "Ways and Means",
        "Finance"
    ]
}